my_module/__init__.py
my_module/my_module.py
my_tourdata-0.0.dist-info/LICENSE
my_tourdata-0.0.dist-info/METADATA
my_tourdata-0.0.dist-info/WHEEL
my_tourdata-0.0.dist-info/top_level.txt
my_tourdata-0.0.dist-info/RECORD
